swarm/__init__.py
swarm/dataset.py
swarm/features.py
swarm/inference.py
swarm/configs/__init__.py
swarm/configs/config.py
swarm/configs/experiments/__init__.py
swarm_rqa_test-0.1.8.dist-info/LICENSE
swarm_rqa_test-0.1.8.dist-info/METADATA
swarm_rqa_test-0.1.8.dist-info/WHEEL
swarm_rqa_test-0.1.8.dist-info/top_level.txt
swarm_rqa_test-0.1.8.dist-info/RECORD
