Metadata-Version: 2.2
Name: swarm_rqa_test
Version: 0.1.8
Summary: SWARM_RQA_TEST
License-File: LICENSE
Requires-Dist: imbalanced-learn==0.12.3
Requires-Dist: joblib==1.4.2
Requires-Dist: matplotlib==3.9.1
Requires-Dist: pandas==2.2.2
Requires-Dist: pyyaml==6.0.1
Requires-Dist: scikit-learn==1.4.0
Requires-Dist: scipy==1.13.1
Requires-Dist: tqdm==4.66
Requires-Dist: xgboost==2.1.0
Requires-Dist: yacs==0.1.8
Requires-Dist: pywavelets==1.6.0
Requires-Dist: plotly-express==0.4.1
Requires-Dist: onnx==1.17.0
Requires-Dist: onnxruntime==1.20.1
Requires-Dist: einops==0.8.0
Dynamic: description
Dynamic: description-content-type
Dynamic: requires-dist
Dynamic: summary
